rg_javascript/__init__.py
rg_javascript/__main__.py
rg_javascript/config.py
rg_javascript/connection.py
rg_javascript/errors.py
rg_javascript/events.py
rg_javascript/json_patch.py
rg_javascript/proxy.py
rg_javascript/pyi.py
rg_javascript/js/bridge.js
rg_javascript/js/deps.js
rg_javascript/js/errors.js
rg_javascript/js/pyi.js
rg_javascript-1!1.0.4.dist-info/LICENSE
rg_javascript-1!1.0.4.dist-info/METADATA
rg_javascript-1!1.0.4.dist-info/WHEEL
rg_javascript-1!1.0.4.dist-info/top_level.txt
rg_javascript-1!1.0.4.dist-info/RECORD
